csv_json/__init__.py
csv_json/csv_json_conv.py
Csv_Json_Converter-1.1.0.dist-info/LICENSE
Csv_Json_Converter-1.1.0.dist-info/METADATA
Csv_Json_Converter-1.1.0.dist-info/WHEEL
Csv_Json_Converter-1.1.0.dist-info/top_level.txt
Csv_Json_Converter-1.1.0.dist-info/RECORD
