Metadata-Version: 2.1
Name: Csv-Json-Converter
Version: 1.1.0
Summary: Аccepts files as input and converts them to csv or json format
Home-page: https://github.com/Rerice
Author: Rerice
Author-email: maxim.covalev@gmail.com
License: UNKNOWN
Platform: UNKNOWN
Requires-Python: >=3.7
